pyconfbox_django/__init__.py
pyconfbox_django/middleware.py
pyconfbox_django/settings.py
pyconfbox_django-0.1.2.dist-info/METADATA
pyconfbox_django-0.1.2.dist-info/WHEEL
pyconfbox_django-0.1.2.dist-info/licenses/LICENSE
pyconfbox_django-0.1.2.dist-info/RECORD
